local_attention/__init__.py
local_attention/local_attention.py
local_attention/rotary.py
local_attention/transformer.py
local_attention-1.11.0.dist-info/LICENSE
local_attention-1.11.0.dist-info/METADATA
local_attention-1.11.0.dist-info/WHEEL
local_attention-1.11.0.dist-info/top_level.txt
local_attention-1.11.0.dist-info/RECORD
