Metadata-Version: 2.2
Name: local-attention
Version: 1.11.0
Summary: Local attention, window with lookback, for language modeling
Home-page: https://github.com/lucidrains/local-attention
Author: Phil Wang
Author-email: lucidrains@gmail.com
License: MIT
Keywords: transformers,attention,artificial intelligence
Classifier: Development Status :: 4 - Beta
Classifier: Intended Audience :: Developers
Classifier: Topic :: Scientific/Engineering :: Artificial Intelligence
Classifier: License :: OSI Approved :: MIT License
Classifier: Programming Language :: Python :: 3.6
License-File: LICENSE
Requires-Dist: einops>=0.8.0
Requires-Dist: hyper-connections>=0.1.8
Requires-Dist: torch
Dynamic: author
Dynamic: author-email
Dynamic: classifier
Dynamic: description-content-type
Dynamic: home-page
Dynamic: keywords
Dynamic: license
Dynamic: requires-dist
Dynamic: summary
